ioexplorer_components
