Metadata-Version: 1.0
Name: ioexplorer-components
Version: 0.1.6
Summary: Components for the IOExplorer Web App
Home-page: UNKNOWN
Author: rmarren1
Author-email: UNKNOWN
License: MIT
Platform: UNKNOWN
